_examples/__init__.py
examples/__init__.py
github_secrets/__init__.py
github_secrets/__main__.py
github_secrets/app.py
github_secrets/cli.py
github_secrets/config.py
github_secrets/console_styles.py
github_secrets/exc.py
github_secrets/git.py
github_secrets/manager.py
tests/__init__.py
tests/config.py
tests/conftest.py
tests/generate.py
tests/test_app.py
tests/test_github.py
tests/test_local.py
tests/test_manager.py
tests/test_sync.py
tests/fixtures/__init__.py
tests/fixtures/model.py
github_secrets-0.1.0.dist-info/LICENSE.md
github_secrets-0.1.0.dist-info/METADATA
github_secrets-0.1.0.dist-info/WHEEL
github_secrets-0.1.0.dist-info/entry_points.txt
github_secrets-0.1.0.dist-info/top_level.txt
github_secrets-0.1.0.dist-info/RECORD
